nep_nao/__init__.py
nep_nao/nao.py
oldne/__init__.py
oldne/behavior_manager.py
oldne/behavior_tree.py
oldne/communication.py
oldne/feedback.py
oldne/interaction.py
oldne/launcher.py
oldne/oldne_helpers.py
oldne/oldne_msg.py
oldne/robot.py
oldnepki/__init__.py
oldnepki/engine.py
oldnepki/nodes.py
oldriz/__init__.py
oldriz/blockly_files.py
oldriz/rize_helpers.py
oldne-1.3.dist-info/METADATA
oldne-1.3.dist-info/WHEEL
oldne-1.3.dist-info/top_level.txt
oldne-1.3.dist-info/RECORD
